xorbits-0.8.2.dist-info/RECORD
xorbits-0.8.2.dist-info/WHEEL
xorbits-0.8.2.dist-info/entry_points.txt
xorbits-0.8.2.dist-info/top_level.txt
xorbits-0.8.2.dist-info/METADATA
xorbits/worker.py
xorbits/conftest.py
xorbits/config.py
xorbits/_version.py
xorbits/supervisor.py
xorbits/__init__.py
xorbits/utils.py
xorbits/experimental/__init__.py
xorbits/experimental/dedup.py
xorbits/experimental/utils.py
xorbits/compat/_constants.py
xorbits/compat/__init__.py
xorbits/core/execution.py
xorbits/core/adapter.py
xorbits/core/__init__.py
xorbits/core/api.py
xorbits/core/data.py
xorbits/core/utils/__init__.py
xorbits/core/utils/docstring.py
xorbits/core/utils/fallback.py
xorbits/web/index_handler.py
xorbits/web/__init__.py
xorbits/web/version_handler.py
xorbits/web/ui/.eslintrc.yml
xorbits/web/ui/index.html
xorbits/web/ui/.prettierrc.yml
xorbits/web/ui/static/187.bundle.js
xorbits/web/ui/static/bundle.js
xorbits/web/ui/static/206.bundle.js
xorbits/web/ui/static/731.bundle.js.LICENSE.txt
xorbits/web/ui/static/bundle.js.LICENSE.txt
xorbits/web/ui/static/124.bundle.js
xorbits/web/ui/static/206.bundle.js.LICENSE.txt
xorbits/web/ui/static/731.bundle.js
xorbits/web/ui/static/resources/assets/images/xorbits.svg
xorbits/web/ui/static/resources/assets/images/favicon.svg
xorbits/deploy/__init__.py
xorbits/deploy/oscar/file-logging.conf
xorbits/deploy/slurm/slurm.py
xorbits/deploy/slurm/__init__.py
xorbits/deploy/kubernetes/worker.py
xorbits/deploy/kubernetes/_constants.py
xorbits/deploy/kubernetes/config.py
xorbits/deploy/kubernetes/supervisor.py
xorbits/deploy/kubernetes/client.py
xorbits/deploy/kubernetes/__init__.py
xorbits/deploy/kubernetes/core.py
xorbits/deploy/kubernetes/config.yml
xorbits/deploy/kubernetes/external_storage/__init__.py
xorbits/deploy/kubernetes/external_storage/external_storage.py
xorbits/deploy/kubernetes/external_storage/juicefs/config.py
xorbits/deploy/kubernetes/external_storage/juicefs/__init__.py
xorbits/xgboost/__init__.py
xorbits/xgboost/test/test_core.py
xorbits/xgboost/test/__init__.py
xorbits/xgboost/mars_adapters/__init__.py
xorbits/xgboost/mars_adapters/core.py
