Metadata-Version: 2.1
Name: xorbits
Version: 0.8.2
Summary: Scalable Python data science, in an API compatible & lightning fast way.
Home-page: http://github.com/xorbitsai/xorbits
Author: Qin Xuye
Author-email: qinxuye@xprobe.io
Maintainer: Qin Xuye
Maintainer-email: qinxuye@xprobe.io
License: Apache License 2.0
Classifier: Operating System :: OS Independent
Classifier: Programming Language :: Python
Classifier: Programming Language :: Python :: 3
Classifier: Programming Language :: Python :: 3.9
Classifier: Programming Language :: Python :: 3.10
Classifier: Programming Language :: Python :: 3.11
Classifier: Programming Language :: Python :: Implementation :: CPython
Classifier: Topic :: Software Development :: Libraries
Provides-Extra: dev
Provides-Extra: doc
Provides-Extra: extra
Provides-Extra: jax
Provides-Extra: kubernetes
Provides-Extra: ray
Provides-Extra: vineyard
Provides-Extra: aws
Provides-Extra: azure
Provides-Extra: datasets
